PIserver/__init__.py
PIserver/cli.py
PIserver/constants.py
PIserver/install.py
PIserver/setup.py
PIserver/clients/FileDownloadClient.py
PIserver/clients/FileUploadClient.py
PIserver/clients/LLMClient.py
PIserver/clients/__init__.py
PIserver/clients/net.py
PIserver/commands/__init__.py
PIserver/commands/clone.py
PIserver/commands/command.py
PIserver/commands/config.py
PIserver/commands/install.py
PIserver/commands/list.py
PIserver/commands/remove.py
PIserver/commands/run.py
PIserver/commands/upload.py
PIserver/utils/__init__.py
PIserver/utils/files.py
PIserver/utils/install.py
powerinfer_server-1.1.1.dist-info/METADATA
powerinfer_server-1.1.1.dist-info/WHEEL
powerinfer_server-1.1.1.dist-info/entry_points.txt
powerinfer_server-1.1.1.dist-info/top_level.txt
powerinfer_server-1.1.1.dist-info/RECORD
