Metadata-Version: 2.4
Name: powerinfer-server
Version: 1.1.1
Summary: A local deployment tool for PowerInfer
Home-page: https://github.com/AliceRayLu/powerinfer-server
Author: ARL
Author-email: aliceraylu0710@gmail.com
Classifier: Programming Language :: Python :: 3
Classifier: License :: OSI Approved :: MIT License
Classifier: Operating System :: OS Independent
Requires-Python: >=3.7
Requires-Dist: fastapi>=0.68.0
Requires-Dist: uvicorn>=0.15.0
Requires-Dist: paramiko>=2.11.0
Requires-Dist: requests>=2.25.0
Requires-Dist: tqdm>=4.61.0
Requires-Dist: tabulate>=0.8.9
Requires-Dist: huggingface_hub>=0.10.1
Requires-Dist: cryptography>=39.0.0
Requires-Dist: keyboard>=0.13.5
Requires-Dist: windows-curses>=2.2.1; sys_platform == "win32"
Dynamic: author
Dynamic: provides-extra
Dynamic: requires-dist
